open_gopro/__init__.py
open_gopro/api/__init__.py
open_gopro/api/api.py
open_gopro/api/ble_commands.py
open_gopro/api/ble_settings.py
open_gopro/api/ble_statuses.py
open_gopro/api/builders.py
open_gopro/api/http_commands.py
open_gopro/api/http_settings.py
open_gopro/database/__init__.py
open_gopro/database/cohn_db.py
open_gopro/demos/__init__.py
open_gopro/demos/cohn.py
open_gopro/demos/connect_wifi.py
open_gopro/demos/gui/__init__.py
open_gopro/demos/gui/livestream.py
open_gopro/demos/gui/preview_stream.py
open_gopro/demos/gui/video_display.py
open_gopro/demos/gui/webcam.py
open_gopro/demos/log_battery.py
open_gopro/demos/multi_camera_sync.py
open_gopro/demos/photo.py
open_gopro/demos/scanner.py
open_gopro/demos/video.py
open_gopro/domain/__init__.py
open_gopro/domain/communicator_interface.py
open_gopro/domain/enum.py
open_gopro/domain/exceptions.py
open_gopro/domain/gopro_observable.py
open_gopro/domain/observable.py
open_gopro/domain/parser_interface.py
open_gopro/features/__init__.py
open_gopro/features/access_point_feature.py
open_gopro/features/base_feature.py
open_gopro/features/cohn_feature.py
open_gopro/features/streaming/__init__.py
open_gopro/features/streaming/base_stream.py
open_gopro/features/streaming/livestream.py
open_gopro/features/streaming/preview_stream.py
open_gopro/features/streaming/stream_feature.py
open_gopro/features/streaming/webcam_stream.py
open_gopro/gopro_base.py
open_gopro/gopro_wired.py
open_gopro/gopro_wireless.py
open_gopro/models/__init__.py
open_gopro/models/bases.py
open_gopro/models/constants/__init__.py
open_gopro/models/constants/constants.py
open_gopro/models/constants/settings.py
open_gopro/models/constants/statuses.py
open_gopro/models/constants/uuids.py
open_gopro/models/general.py
open_gopro/models/media_list.py
open_gopro/models/network_scan_responses.py
open_gopro/models/proto/__init__.py
open_gopro/models/proto/camera_control_pb2.py
open_gopro/models/proto/camera_control_pb2.pyi
open_gopro/models/proto/cohn_pb2.py
open_gopro-0.22.0.dist-info/METADATA
open_gopro-0.22.0.dist-info/WHEEL
open_gopro-0.22.0.dist-info/entry_points.txt
open_gopro-0.22.0.dist-info/licenses/LICENSE
open_gopro-0.22.0.dist-info/RECORD
