Metadata-Version: 2.4
Name: open_gopro
Version: 0.22.0
Summary: Open GoPro API and Examples
License: MIT
License-File: LICENSE
Author: Tim Camise
Author-email: tcamise@gopro.com
Requires-Python: >=3.11,<3.14
Classifier: Intended Audience :: Developers
Classifier: License :: OSI Approved :: MIT License
Classifier: Natural Language :: English
Classifier: Operating System :: MacOS :: MacOS X
Classifier: Operating System :: Microsoft :: Windows :: Windows 10
Classifier: Operating System :: POSIX :: Linux
Classifier: Programming Language :: Python
Classifier: Programming Language :: Python :: 3
Classifier: Programming Language :: Python :: 3.11
Classifier: Programming Language :: Python :: 3.12
Classifier: Programming Language :: Python :: 3.13
Classifier: Topic :: Communications
Provides-Extra: gui
Requires-Dist: Pillow (>=11,<12) ; extra == "gui"
Requires-Dist: asyncstdlib (>=3,<4)
Requires-Dist: bleak (==0.22.3)
Requires-Dist: construct (>=2,<3)
Requires-Dist: opencv-python (>=4,<5) ; extra == "gui"
Requires-Dist: packaging (==25)
Requires-Dist: pexpect (>=4,<5)
Requires-Dist: protobuf (>=6,<7)
Requires-Dist: pydantic (>=2,<3)
Requires-Dist: pytz
Requires-Dist: requests (>=2,<3)
Requires-Dist: returns[compatible-mypy] (>=0,<1)
Requires-Dist: rich (>=14,<15)
Requires-Dist: tinydb (>=4,<5)
Requires-Dist: tzlocal
Requires-Dist: wrapt (>=1,<2)
Requires-Dist: zeroconf (>=0,<1)
Project-URL: Documentation, https://gopro.github.io/OpenGoPro/python_sdk/
Project-URL: Repository, https://github.com/gopro/OpenGoPro/tree/main/demos/python/sdk_wireless_camera_control
